CHANGELOG.md
LICENSE
MANIFEST.in
README.md
requirements.txt
setup.py
chemdataextractor/__init__.py
chemdataextractor/config.py
chemdataextractor/data.py
chemdataextractor/errors.py
chemdataextractor/fastner.py
chemdataextractor/utils.py
chemdataextractor2.egg-info/PKG-INFO
chemdataextractor2.egg-info/SOURCES.txt
chemdataextractor2.egg-info/dependency_links.txt
chemdataextractor2.egg-info/entry_points.txt
chemdataextractor2.egg-info/not-zip-safe
chemdataextractor2.egg-info/requires.txt
chemdataextractor2.egg-info/top_level.txt
chemdataextractor/biblio/__init__.py
chemdataextractor/biblio/bibtex.py
chemdataextractor/biblio/person.py
chemdataextractor/biblio/xmp.py
chemdataextractor/cli/__init__.py
chemdataextractor/cli/cem.py
chemdataextractor/cli/chemdner.py
chemdataextractor/cli/cluster.py
chemdataextractor/cli/config.py
chemdataextractor/cli/data.py
chemdataextractor/cli/dict.py
chemdataextractor/cli/evaluate.py
chemdataextractor/cli/pos.py
chemdataextractor/cli/tokenize.py
chemdataextractor/doc/__init__.py
chemdataextractor/doc/document.py
chemdataextractor/doc/document_cacher.py
chemdataextractor/doc/element.py
chemdataextractor/doc/figure.py
chemdataextractor/doc/meta.py
chemdataextractor/doc/table.py
chemdataextractor/doc/text.py
chemdataextractor/eval/__init__.py
chemdataextractor/eval/evaluation.py
chemdataextractor/model/__init__.py
chemdataextractor/model/base.py
chemdataextractor/model/confidence_pooling.py
chemdataextractor/model/contextual_range.py
chemdataextractor/model/model.py
chemdataextractor/model/units/__init__.py
chemdataextractor/model/units/angle.py
chemdataextractor/model/units/charge.py
chemdataextractor/model/units/current.py
chemdataextractor/model/units/dimension.py
chemdataextractor/model/units/electric_potential.py
chemdataextractor/model/units/energy.py
chemdataextractor/model/units/length.py
chemdataextractor/model/units/mass.py
chemdataextractor/model/units/power.py
chemdataextractor/model/units/quantity_model.py
chemdataextractor/model/units/ratio.py
chemdataextractor/model/units/substance_amount.py
chemdataextractor/model/units/temperature.py
chemdataextractor/model/units/time.py
chemdataextractor/model/units/unit.py
chemdataextractor/nlp/__init__.py
chemdataextractor/nlp/abbrev.py
